wom_connector/__init__.py
wom_connector/crypto.py
wom_connector/filter.py
wom_connector/instrument.py
wom_connector/models.py
wom_connector/pointofsale.py
wom_connector/registry_proxy.py
wom_connector/rest_client.py
wom_connector/voucher.py
wom_connector/wom_logger.py
wom_connector-1.1.0.dist-info/METADATA
wom_connector-1.1.0.dist-info/WHEEL
wom_connector-1.1.0.dist-info/top_level.txt
wom_connector-1.1.0.dist-info/RECORD
