Metadata-Version: 2.1
Name: wom-connector
Version: 1.1.0
Summary: Connector library to the WOM Platform.
Home-page: https://github.com/WOM-Platform/Python-Connector
Author: WOM Platform
Author-email: info@wom.social
License: MIT
Project-URL: Homepage, https://wom.social/
Project-URL: Source, https://github.com/WOM-Platform/Python-Connector
Platform: UNKNOWN
Requires-Dist: requests (>=2.25.1)
Requires-Dist: cryptography (>=2.9.2)
